litchi/__init__.py
litchi/cli/__init__.py
litchi/cli/chat_command.py
litchi/cli/common_util.py
litchi/cli/gen_command.py
litchi/cli/gendata_command.py
litchi/cli/image_command.py
litchi/cli/index_command.py
litchi/cli/init_command.py
litchi/cli/main.py
litchi/cli/opt_command.py
litchi/cli/optfile_command.py
litchi/cli/source_command.py
litchi/cli/watch_command.py
litchi/config_util/__init__.py
litchi/config_util/litchi_config.py
litchi/index_util/__init__.py
litchi/index_util/index_manager.py
litchi/index_util/llm_util.py
litchi/index_util/sqlite_util.py
litchi/prompt_util/__init__.py
litchi/prompt_util/analyse_source_file.prompt
litchi/prompt_util/chat_with_realted_source_files.prompt
litchi/prompt_util/gencode.prompt
litchi/prompt_util/genfile.prompt
litchi/prompt_util/get_related_source_files.prompt
litchi/prompt_util/optcode.prompt
litchi/prompt_util/optfile.prompt
litchi/prompt_util/prompt_util.py
litchi/source_util/__init__.py
litchi/source_util/file_util.py
litchi/source_util/source_file_manager.py
litchi/watcher_util/__init__.py
litchi/watcher_util/file_watcher.py
orchard_litchi-0.1.2.dist-info/LICENSE
orchard_litchi-0.1.2.dist-info/METADATA
orchard_litchi-0.1.2.dist-info/WHEEL
orchard_litchi-0.1.2.dist-info/entry_points.txt
orchard_litchi-0.1.2.dist-info/top_level.txt
orchard_litchi-0.1.2.dist-info/RECORD
