Metadata-Version: 2.1
Name: orchard-litchi
Version: 0.1.2
Summary: Litchi is yet another coding assistant powered by LLM.
Home-page: https://github.com/OrchardUniverse/litchi
Author: Orchard Universe
Classifier: Programming Language :: Python :: 3
Classifier: License :: OSI Approved :: MIT License
Classifier: Operating System :: OS Independent
Requires-Python: >=3.6
License-File: LICENSE
Requires-Dist: openai
Requires-Dist: watchdog
Requires-Dist: click
Requires-Dist: pyyaml
Requires-Dist: prettytable
Requires-Dist: jinja2
Requires-Dist: coloredlogs
